Metadata-Version: 2.4
Name: pagerduty-mcp
Version: 0.12.0
Summary: PagerDuty's official local MCP (Model Context Protocol) server which provides tools to interact with your PagerDuty account directly from your MCP-enabled client.
Requires-Python: ~=3.12.0
License-File: LICENSE
Requires-Dist: mcp[cli]~=1.8
Requires-Dist: pagerduty~=5.3
Requires-Dist: typer~=0.16.0
Dynamic: license-file
